typeagent/__init__.py
typeagent/py.typed
typeagent/aitools/auth.py
typeagent/aitools/embeddings.py
typeagent/aitools/utils.py
typeagent/aitools/vectorbase.py
typeagent/emails/emailVerbs.json
typeagent/emails/email_import.py
typeagent/emails/email_memory.py
typeagent/emails/email_message.py
typeagent/emails/noiseTerms.txt
typeagent/knowpro/answer_context_schema.py
typeagent/knowpro/answer_response_schema.py
typeagent/knowpro/answers.py
typeagent/knowpro/collections.py
typeagent/knowpro/common.py
typeagent/knowpro/conversation_base.py
typeagent/knowpro/convknowledge.py
typeagent/knowpro/convsettings.py
typeagent/knowpro/convutils.py
typeagent/knowpro/date_time_schema.py
typeagent/knowpro/factory.py
typeagent/knowpro/field_helpers.py
typeagent/knowpro/fuzzyindex.py
typeagent/knowpro/interfaces.py
typeagent/knowpro/knowledge.py
typeagent/knowpro/kplib.py
typeagent/knowpro/messageutils.py
typeagent/knowpro/query.py
typeagent/knowpro/search.py
typeagent/knowpro/search_query_schema.py
typeagent/knowpro/searchlang.py
typeagent/knowpro/searchlib.py
typeagent/knowpro/secindex.py
typeagent/knowpro/serialization.py
typeagent/knowpro/textlocindex.py
typeagent/knowpro/universal_message.py
typeagent/knowpro/utils.py
typeagent/mcp/server.py
typeagent/podcasts/podcast.py
typeagent/podcasts/podcastVerbs.json
typeagent/podcasts/podcast_ingest.py
typeagent/storage/__init__.py
typeagent/storage/utils.py
typeagent/storage/memory/__init__.py
typeagent/storage/memory/collections.py
typeagent/storage/memory/convthreads.py
typeagent/storage/memory/messageindex.py
typeagent/storage/memory/propindex.py
typeagent/storage/memory/provider.py
typeagent/storage/memory/reltermsindex.py
typeagent/storage/memory/semrefindex.py
typeagent/storage/memory/timestampindex.py
typeagent/storage/sqlite/__init__.py
typeagent/storage/sqlite/collections.py
typeagent/storage/sqlite/messageindex.py
typeagent/storage/sqlite/propindex.py
typeagent/storage/sqlite/provider.py
typeagent/storage/sqlite/reltermsindex.py
typeagent-0.3.2.dist-info/licenses/LICENSE
typeagent-0.3.2.dist-info/METADATA
typeagent-0.3.2.dist-info/WHEEL
typeagent-0.3.2.dist-info/top_level.txt
typeagent-0.3.2.dist-info/RECORD
